django_encryption/__init__.py
django_encryption/aes.py
django_encryption/client.py
django_encryption/config.py
django_encryption/constants.py
django_encryption/context.py
django_encryption/datakeeper.py
django_encryption/field.py
django_encryption/model.py
django_encryption_sdk-1.1.16.dist-info/METADATA
django_encryption_sdk-1.1.16.dist-info/WHEEL
django_encryption_sdk-1.1.16.dist-info/top_level.txt
django_encryption_sdk-1.1.16.dist-info/RECORD
